LICENSE
MANIFEST.in
README.rst
setup.py
django_hosted_plugins.egg-info/PKG-INFO
django_hosted_plugins.egg-info/SOURCES.txt
django_hosted_plugins.egg-info/dependency_links.txt
django_hosted_plugins.egg-info/not-zip-safe
django_hosted_plugins.egg-info/requires.txt
django_hosted_plugins.egg-info/top_level.txt
hosted_plugins/__init__.py
hosted_plugins/admin.py
hosted_plugins/apps.py
hosted_plugins/models.py
hosted_plugins/permissions.py
hosted_plugins/serializers.py
hosted_plugins/tests.py
hosted_plugins/urls.py
hosted_plugins/views.py
hosted_plugins/migrations/0001_initial.py
hosted_plugins/migrations/__init__.py