Metadata-Version: 1.1
Name: django-hosted-plugins
Version: 0.1.1
Summary: Self host third-party plugins that work alongside your project.
Home-page: https://pypi.python.org/pypi/django-hosted-plugins/
Author: Vimal Aravindashan
Author-email: vimal.aravindashan@gmail.com
License: MIT
Platform: any
Classifier: Environment :: Web Environment
Classifier: Framework :: Django
Classifier: Framework :: Django :: 1.8
Classifier: Intended Audience :: Developers
Classifier: License :: OSI Approved :: MIT License
Classifier: Operating System :: OS Independent
Classifier: Programming Language :: Python
Classifier: Programming Language :: Python :: 2
Classifier: Programming Language :: Python :: 2.7
Classifier: Topic :: Internet :: WWW/HTTP
Classifier: Topic :: Internet :: WWW/HTTP :: Dynamic Content
